repomaker/__init__.py
repomaker/admin.py
repomaker/apps.py
repomaker/gui.py
repomaker/settings.py
repomaker/settings_desktop.py
repomaker/settings_test.py
repomaker/settings_test_multi_user.py
repomaker/storage.py
repomaker/tasks.py
repomaker/urls.py
repomaker/utils.py
repomaker/wsgi.py
repomaker/locale/django.pot
repomaker/locale/djangojs.pot
repomaker/locale/bo/LC_MESSAGES/django.mo
repomaker/locale/bo/LC_MESSAGES/django.po
repomaker/locale/bo/LC_MESSAGES/djangojs.mo
repomaker/locale/bo/LC_MESSAGES/djangojs.po
repomaker/locale/ca/LC_MESSAGES/django.mo
repomaker/locale/ca/LC_MESSAGES/django.po
repomaker/locale/ca/LC_MESSAGES/djangojs.mo
repomaker/locale/ca/LC_MESSAGES/djangojs.po
repomaker/locale/de/LC_MESSAGES/django.mo
repomaker/locale/de/LC_MESSAGES/django.po
repomaker/locale/de/LC_MESSAGES/djangojs.mo
repomaker/locale/de/LC_MESSAGES/djangojs.po
repomaker/locale/es/LC_MESSAGES/django.mo
repomaker/locale/es/LC_MESSAGES/django.po
repomaker/locale/es/LC_MESSAGES/djangojs.mo
repomaker/locale/es/LC_MESSAGES/djangojs.po
repomaker/locale/fa/LC_MESSAGES/django.mo
repomaker/locale/fa/LC_MESSAGES/django.po
repomaker/locale/fa/LC_MESSAGES/djangojs.mo
repomaker/locale/fa/LC_MESSAGES/djangojs.po
repomaker/locale/fr/LC_MESSAGES/django.mo
repomaker/locale/fr/LC_MESSAGES/django.po
repomaker/locale/fr/LC_MESSAGES/djangojs.mo
repomaker/locale/fr/LC_MESSAGES/djangojs.po
repomaker/locale/it/LC_MESSAGES/django.mo
repomaker/locale/it/LC_MESSAGES/django.po
repomaker/locale/it/LC_MESSAGES/djangojs.mo
repomaker/locale/it/LC_MESSAGES/djangojs.po
repomaker/locale/ko/LC_MESSAGES/django.mo
repomaker/locale/ko/LC_MESSAGES/django.po
repomaker/locale/ko/LC_MESSAGES/djangojs.mo
repomaker/locale/ko/LC_MESSAGES/djangojs.po
repomaker/locale/nb_NO/LC_MESSAGES/django.mo
repomaker/locale/nb_NO/LC_MESSAGES/django.po
repomaker/locale/nb_NO/LC_MESSAGES/djangojs.mo
repomaker/locale/nb_NO/LC_MESSAGES/djangojs.po
repomaker/locale/nl/LC_MESSAGES/django.mo
repomaker-1.0.0b1.dist-info/DESCRIPTION.rst
repomaker-1.0.0b1.dist-info/METADATA
repomaker-1.0.0b1.dist-info/RECORD
repomaker-1.0.0b1.dist-info/WHEEL
repomaker-1.0.0b1.dist-info/entry_points.txt
repomaker-1.0.0b1.dist-info/metadata.json
repomaker-1.0.0b1.dist-info/top_level.txt
