Metadata-Version: 2.0
Name: repomaker
Version: 1.0.0b1
Summary: Create F-Droid repositories with ease
Home-page: https://f-droid.org/repomaker/
Author: F-Droid Community
Author-email: team@f-droid.org
License: AGPL-3.0
Keywords: android,app store,repository
Platform: UNKNOWN
Classifier: Development Status :: 5 - Production/Stable
Classifier: Intended Audience :: Developers
Classifier: Intended Audience :: End Users/Desktop
Classifier: Environment :: Web Environment
Classifier: Framework :: Django
Classifier: License :: OSI Approved :: GNU Affero General Public License v3 or later (AGPLv3+)
Classifier: Programming Language :: Python :: 3.4
Classifier: Programming Language :: Python :: 3.5
Classifier: Programming Language :: Python :: 3.6
Classifier: Topic :: Utilities
Classifier: Topic :: System :: Software Distribution
Requires-Python: >=3, <3.7
Requires-Dist: bleach (>=2.1.4)
Requires-Dist: cryptography (>=1.4.0)
Requires-Dist: django (<2.0)
Requires-Dist: django-allauth
Requires-Dist: django-background-tasks (==1.1.13)
Requires-Dist: django-compressor
Requires-Dist: django-hvad (>=1.8.0)
Requires-Dist: django-js-reverse
Requires-Dist: django-sass-processor
Requires-Dist: django-tinymce
Requires-Dist: fdroidserver (==0.8)
Requires-Dist: python-magic
Requires-Dist: qrcode
Requires-Dist: six (>=1.9)
Provides-Extra: gui
Requires-Dist: PyQt5 (==5.10.0); extra == 'gui'
Requires-Dist: pywebview[qt5]; extra == 'gui'
Provides-Extra: test
Requires-Dist: coverage; extra == 'test'
Requires-Dist: pep8; extra == 'test'
Requires-Dist: pylint-django; extra == 'test'
